hrconv/__init__.py
hrconv/hrc.py
hrconv/observer.py
tests/__init__.py
tests/test_batch.py
hrconv-0.3.0.dist-info/LICENSE
hrconv-0.3.0.dist-info/METADATA
hrconv-0.3.0.dist-info/WHEEL
hrconv-0.3.0.dist-info/top_level.txt
hrconv-0.3.0.dist-info/RECORD
