Metadata-Version: 2.2
Name: hrconv
Version: 0.3.0
Summary: A Python library for convolving and deconvolving mne NIRS objects with a dynamically built hemodynamic response function to remove temporal blur from brain signals
Home-page: https://github.com/dennys246/hrc
Author: Denny Schaedig
Author-email: denny.schaedig@gmail.com
Classifier: Programming Language :: Python :: 3
Classifier: License :: OSI Approved :: MIT License
Classifier: Operating System :: OS Independent
Requires-Python: >=3.0
License-File: LICENSE
Requires-Dist: requests
Dynamic: author
Dynamic: author-email
Dynamic: classifier
Dynamic: home-page
Dynamic: requires-dist
Dynamic: requires-python
Dynamic: summary
